py_acr122u/__init__.py
py_acr122u/error.py
py_acr122u/nfc.py
py_acr122u/option.py
py_acr122u/utils.py
py_acr122u-2.3.0.dist-info/LICENSE
py_acr122u-2.3.0.dist-info/METADATA
py_acr122u-2.3.0.dist-info/WHEEL
py_acr122u-2.3.0.dist-info/top_level.txt
py_acr122u-2.3.0.dist-info/RECORD
